{
    "builds": [
        {
            "id": 5082857,
            "uuid": "df486980-c4e6-0132-563f-023fe0902630",
            "project_id": 34082,
            "status": "success",
            "github_username": "mcgaffin",
            "commit_id": "811e2a3a5a8d88334af6ca4566f2757a6ad6960e",
            "message": "Merge pull request #21 from codeship/add-coc\n\nadd Code of Conduct",
            "branch": "v1.1.9",
            "started_at": "2015-04-14T15:14:30.320Z",
            "finished_at": "2015-04-14T15:15:02.143Z"
        },
        {
            "id": 5075228,
            "uuid": "1bfa37b0-c4b9-0132-b6b8-0e929ca8a996",
            "project_id": 34082,
            "status": "success",
            "github_username": "mcgaffin",
            "commit_id": "b6c3753b21df9248b65708ef64d0b2ace24c9b0c",
            "message": "Merge pull request #21 from codeship/add-coc\n\nadd Code of Conduct",
            "branch": "master",
            "started_at": "2015-04-14T09:46:55.299Z",
            "finished_at": "2015-04-14T09:47:43.085Z"
        },
        {
            "id": 5072548,
            "uuid": "5d829040-c4a0-0132-b6b8-0e929ca8a996",
            "project_id": 34082,
            "status": "success",
            "github_username": "beanieboi",
            "commit_id": "de80a210a6643ddfbbcd04951f13ade781443f9b",
            "message": "add Code of Conduct",
            "branch": "add-coc",
            "started_at": "2015-04-14T06:49:47.827Z",
            "finished_at": "2015-04-14T06:50:19.544Z"
        },
        {
            "id": 5050563,
            "uuid": "b2dd73a0-c3ef-0132-7c3b-42ee6e2a9c35",
            "project_id": 34082,
            "status": "success",
            "github_username": "mcgaffin",
            "commit_id": "dfbcf42113f98c835c05f945302134caf6673e1d",
            "message": "Merge branch 'master' into feature/select_projects",
            "branch": "feature/select_projects",
            "started_at": "2015-04-13T09:48:53.416Z",
            "finished_at": "2015-04-13T09:49:25.104Z"
        },
        {
            "id": 5050509,
            "uuid": "6a774390-c3ef-0132-7c3b-42ee6e2a9c35",
            "project_id": 34082,
            "status": "success",
            "github_username": "beanieboi",
            "commit_id": "880471f9d5bbb0e7b0df3295a7ec7b13bc65326b",
            "message": "Merge pull request #20 from codeship/ben-api-refactor\n\nUpdate API usage to use new Projects API. Builds are now loaded via separate requests. [resolve #16]",
            "branch": "master",
            "started_at": "2015-04-13T09:43:08.655Z",
            "finished_at": "2015-04-13T09:43:40.388Z"
        },
        {
            "id": 5050123,
            "uuid": "267ca380-c3ec-0132-2ada-12d6964a851c",
            "project_id": 34082,
            "status": "success",
            "github_username": "mcgaffin",
            "commit_id": "319fc4d7a6d03a42552a570b5877d5e25c35e5a0",
            "message": "merge from ben-api-refactor",
            "branch": "feature/select_projects",
            "started_at": "2015-04-13T09:19:46.264Z",
            "finished_at": "2015-04-13T09:21:06.686Z"
        },
        {
            "id": 4673514,
            "uuid": "9048a2d0-b2b4-0132-980e-0ee83f5e575b",
            "project_id": 34082,
            "status": "success",
            "github_username": "beanieboi",
            "commit_id": "3ff59967b96ceda83acbc51a47a5162c0da7c0cc",
            "message": "proper check for undefined",
            "branch": "ben-api-refactor",
            "started_at": "2015-04-05T20:58:06.575Z",
            "finished_at": "2015-04-05T20:58:38.056Z"
        },
        {
            "id": 4582101,
            "uuid": "f357e680-aeda-0132-e0f6-3abeb12dede3",
            "project_id": 34082,
            "status": "success",
            "github_username": "mcgaffin",
            "commit_id": "caa7c17f616dc87cfcb435d97bd6f47c78b89e3b",
            "message": "fix bug: close options dialog when valid api key is entered.",
            "branch": "ben-api-refactor",
            "started_at": "2015-03-17T13:53:44.440Z",
            "finished_at": "2015-03-17T13:54:16.295Z"
        },
        {
            "id": 4566970,
            "uuid": "ec7ac120-ae41-0132-9e2c-7628c9d9f630",
            "project_id": 34082,
            "status": "success",
            "github_username": "mcgaffin",
            "commit_id": "9eefd996801c7a9d2745e758b1eff9f68a3df23b",
            "message": "updated node dev dependencies",
            "branch": "ben-api-refactor",
            "started_at": "2015-03-16T19:38:19.915Z",
            "finished_at": "2015-03-16T19:38:56.788Z"
        },
        {
            "id": 4565424,
            "uuid": "3dd2c250-ae38-0132-9e2c-7628c9d9f630",
            "project_id": 34082,
            "status": "success",
            "github_username": "mcgaffin",
            "commit_id": "d814f5273f3b13a23e9fd650a80d215589651cb9",
            "message": "restored minified files to build.",
            "branch": "ben-api-refactor",
            "started_at": "2015-03-16T18:29:01.420Z",
            "finished_at": "2015-03-16T18:29:33.595Z"
        },
        {
            "id": 4564841,
            "uuid": "de789ad0-ae34-0132-c731-520955e28d52",
            "project_id": 34082,
            "status": "success",
            "github_username": "mcgaffin",
            "commit_id": "e982c08415f3aaca7512c1b16c72712c84ea35ae",
            "message": "fixed project specs",
            "branch": "ben-api-refactor",
            "started_at": "2015-03-16T18:27:13.610Z",
            "finished_at": "2015-03-16T18:27:45.288Z"
        },
        {
            "id": 4563750,
            "uuid": "08a43510-ae2f-0132-c731-520955e28d52",
            "project_id": 34082,
            "status": "error",
            "github_username": "mcgaffin",
            "commit_id": "70a447625e44944f877fb896bf0f6c397bf202d5",
            "message": "fixed build_watcher specs.",
            "branch": "ben-api-refactor",
            "started_at": "2015-03-16T17:23:06.727Z",
            "finished_at": "2015-03-16T17:23:39.095Z"
        },
        {
            "id": 4556977,
            "uuid": "271ab7e0-ae0a-0132-ba7c-6aa154d7f26d",
            "project_id": 34082,
            "status": "error",
            "github_username": "mcgaffin",
            "commit_id": "b573f13e2b342b12662385942e7de0c85d48810d",
            "message": "fixed most of the broken specs",
            "branch": "ben-api-refactor",
            "started_at": "2015-03-16T12:59:06.455Z",
            "finished_at": "2015-03-16T12:59:42.089Z"
        },
        {
            "id": 4556976,
            "uuid": "26b74410-ae0a-0132-ba7c-6aa154d7f26d",
            "project_id": 34082,
            "status": "success",
            "github_username": "mcgaffin",
            "commit_id": "c5717aac8ef21468d1cd8045dfef327c80980d5e",
            "message": "bump version for 1.1.8",
            "branch": "v1.1.8",
            "started_at": "2015-03-16T12:59:05.806Z",
            "finished_at": "2015-03-16T12:59:37.408Z"
        },
        {
            "id": 4533129,
            "uuid": "cba7f6f0-abd8-0132-a3af-42fedf98caeb",
            "project_id": 34082,
            "status": "error",
            "github_username": "beanieboi",
            "commit_id": "283c8af0cc0ae0c37f555be2343a9d0a64bfa2bf",
            "message": "attempt to fix bugs",
            "branch": "ben-api-refactor",
            "started_at": "2015-03-13T18:00:45.365Z",
            "finished_at": "2015-03-13T18:01:17.859Z"
        },
        {
            "id": 4531929,
            "uuid": "b1a33c40-abd0-0132-a3af-42fedf98caeb",
            "project_id": 34082,
            "status": "error",
            "github_username": "beanieboi",
            "commit_id": "a41b4dce59968a395dae879a453970ac433d24ad",
            "message": "fix build view",
            "branch": "ben-api-refactor",
            "started_at": "2015-03-13T17:02:45.739Z",
            "finished_at": "2015-03-13T17:03:54.516Z"
        },
        {
            "id": 4531727,
            "uuid": "6350eb60-abcf-0132-a3af-42fedf98caeb",
            "project_id": 34082,
            "status": "error",
            "github_username": "beanieboi",
            "commit_id": "8bb86f00a2fbc13649fba4259f94e92b86ee396e",
            "message": "remove ,",
            "branch": "ben-api-refactor",
            "started_at": "2015-03-13T16:53:24.840Z",
            "finished_at": "2015-03-13T16:54:02.385Z"
        },
        {
            "id": 4531681,
            "uuid": "2ca95100-abcf-0132-a3af-42fedf98caeb",
            "project_id": 34082,
            "status": "error",
            "github_username": "beanieboi",
            "commit_id": "9117ae42d61511f7a576bd56de29ba020960b882",
            "message": "revert changes",
            "branch": "ben-api-refactor",
            "started_at": "2015-03-13T16:51:53.145Z",
            "finished_at": "2015-03-13T16:52:25.129Z"
        },
        {
            "id": 4531583,
            "uuid": "9f698d00-abce-0132-a3af-42fedf98caeb",
            "project_id": 34082,
            "status": "error",
            "github_username": "beanieboi",
            "commit_id": "c01c6cbb7d32bc24a66fbae7eeb59bfbcd790331",
            "message": "fix duplicated methods",
            "branch": "ben-api-refactor",
            "started_at": "2015-03-13T16:47:56.168Z",
            "finished_at": "2015-03-13T16:48:22.800Z"
        },
        {
            "id": 4531194,
            "uuid": "34b833d0-abcc-0132-a3af-42fedf98caeb",
            "project_id": 34082,
            "status": "error",
            "github_username": "beanieboi",
            "commit_id": "611d5c335f3e8a46959c8b83be3ec85722e9553d",
            "message": "init buildCollection after passing to the frontend",
            "branch": "ben-api-refactor",
            "started_at": "2015-03-13T16:30:38.174Z",
            "finished_at": "2015-03-13T16:31:09.885Z"
        },
        {
            "id": 4530480,
            "uuid": "41097cb0-abc8-0132-a3af-42fedf98caeb",
            "project_id": 34082,
            "status": "error",
            "github_username": "mcgaffin",
            "commit_id": "7a3f38af526aac46d4e8f0defd0d8bb7b14e5e07",
            "message": "iterating on fixing new api work",
            "branch": "ben-api-refactor",
            "started_at": "2015-03-13T16:02:20.853Z",
            "finished_at": "2015-03-13T16:02:50.240Z"
        },
        {
            "id": 4527110,
            "uuid": "432f34b0-abb3-0132-a3af-42fedf98caeb",
            "project_id": 34082,
            "status": "success",
            "github_username": "mcgaffin",
            "commit_id": "d217070a7098916742cebd0933e7225bc5e10df9",
            "message": "partial, broken implementation",
            "branch": "feature/select_projects",
            "started_at": "2015-03-13T17:41:58.135Z",
            "finished_at": "2015-03-13T17:42:29.481Z"
        },
        {
            "id": 4523798,
            "uuid": "605dacb0-ab96-0132-06f1-5e8b7c217dbb",
            "project_id": 34082,
            "status": "error",
            "github_username": "beanieboi",
            "commit_id": "9e403ab78a6643a3502894b6c3f21d93f8b04415",
            "message": "add CodeshipApi to karma.conf",
            "branch": "ben-api-refactor",
            "started_at": "2015-03-13T10:05:18.589Z",
            "finished_at": "2015-03-13T10:05:50.276Z"
        },
        {
            "id": 4522819,
            "uuid": "45a95340-ab8b-0132-06f1-5e8b7c217dbb",
            "project_id": 34082,
            "status": "error",
            "github_username": "beanieboi",
            "commit_id": "32576974b8a6f99702abbef4e574bb404277622b",
            "message": "fix projects view",
            "branch": "ben-api-refactor",
            "started_at": "2015-03-13T08:45:49.310Z",
            "finished_at": "2015-03-13T08:46:37.009Z"
        },
        {
            "id": 4522214,
            "uuid": "0a838470-ab81-0132-06f1-5e8b7c217dbb",
            "project_id": 34082,
            "status": "error",
            "github_username": "beanieboi",
            "commit_id": "9715c63b9671d2f94291dcd4afafd67325bebd36",
            "message": "starting to refactor into CodeshipApi",
            "branch": "ben-api-refactor",
            "started_at": "2015-03-13T07:32:35.112Z",
            "finished_at": "2015-03-13T07:33:12.205Z"
        }
    ]
}
